bitfarmer/__init__.py
bitfarmer/bitfarmer.egg-info/PKG-INFO
bitfarmer/bitfarmer.egg-info/SOURCES.txt
bitfarmer/bitfarmer.egg-info/dependency_links.txt
bitfarmer/bitfarmer.egg-info/entry_points.txt
bitfarmer/bitfarmer.egg-info/requires.txt
bitfarmer/bitfarmer.egg-info/top_level.txt
bitfarmer/bitfarmer.py
bitfarmer/coloring.py
bitfarmer/config.py
bitfarmer/elphapex.py
bitfarmer/log.py
bitfarmer/miner.py
bitfarmer/ntp.py
bitfarmer/volcminer.py
bitfarmer-0.1.1.dist-info/LICENSE
bitfarmer-0.1.1.dist-info/METADATA
bitfarmer-0.1.1.dist-info/WHEEL
bitfarmer-0.1.1.dist-info/RECORD
