Metadata-Version: 2.1
Name: bitfarmer
Version: 0.1.1
Summary: ASIC manager
License: GNU General Public License v3.0
Author: jandrus
Author-email: jandrus@citadel.edu
Requires-Python: >=3.13,<4.0
Classifier: License :: Other/Proprietary License
Classifier: Programming Language :: Python :: 3
Classifier: Programming Language :: Python :: 3.13
Requires-Dist: colorama (>=0.4.6)
Requires-Dist: ntplib (>=0.4.0)
Requires-Dist: platformdirs (>=4.3.6)
Requires-Dist: requests (>=2.23.0)
Requires-Dist: yaspin (>=3.1.0)
